{"title":"Mobil & İletişim","subcategories":[{"title":"Android Modlar","links":[{"url":"https://premiertvapps.blogspot.com/","name":"Premier TV","recommended":false,"description":"Canlı TV ve yayınlar için modlu Android uygulaması.","icon":"icon/premiertv.svg","alt":"Premier TV","tags":["premier","premiertvapps","blogspot"],"folded":"premier tv premier premiertvapps blogspot mobil & iletisim android modlar diger digerleri"},{"url":"https://vanced.to/","name":"ReVanced Manager","recommended":false,"description":"YouTube Vanced ve benzeri modlu Android uygulamaları.","icon":"icon/vanced.svg","alt":"ReVanced Manager","tags":["revanced","manager","paket yöneticisi","vanced"],"folded":"revanced manager revanced manager paket yoneticisi vanced mobil & iletisim android modlar diger digerleri"},{"url":"https://www.xmanagerapp.com/","name":"xManager","recommended":false,"description":"Spotify için reklamsız ve gelişmiş Android uygulama yöneticisi.","icon":"icon/xmanager.svg","alt":"xManager","tags":["xmanager","müzik","paket yöneticisi","xmanagerapp"],"folded":"xmanager xmanager muzik paket yoneticisi xmanagerapp mobil & iletisim android modlar diger digerleri"},{"url":"https://www.instamod.co/","name":"InstaPro","recommended":false,"description":"Instagram için reklamsız ve gelişmiş özellikler sunan modlu uygulama.","icon":"icon/instapro.svg","alt":"InstaPro","tags":["instapro","instamod"],"folded":"instapro instapro instamod mobil & iletisim android modlar diger digerleri"},{"url":"https://t.me/netvgoldbilgi_bot","name":"Ne TV Gold","recommended":false,"description":"Canlı TV ve yayınlar için modlu Android uygulaması.","icon":"icon/netvgold.svg","alt":"Ne TV Gold","tags":["gold","netvgold","github"],"folded":"ne tv gold gold netvgold github mobil & iletisim android modlar diger digerleri"},{"url":"https://t.me/inattvadmin","name":"İnat TV","recommended":false,"description":"Canlı TV ve yayınlar için modlu Android uygulaması.","icon":"icon/inattv.svg","alt":"İnat TV","tags":["inat","inattv156","cfd"],"folded":"inat tv inat inattv156 cfd mobil & iletisim android modlar diger digerleri"},{"url":"https://t.me/instaprimeofficial","name":"InstaPrime","recommended":false,"description":"Biz sadece başka bir mod değiliz — özgürlüğünüz, gizliliğiniz ve deneyiminiz üzerine kurulu bir hareketiz.","icon":"icon/instaprime.svg","alt":"InstaPrime","tags":["instaprime","instaprimeofficial","instagram","telegram"],"folded":"instaprime instaprime instaprimeofficial instagram telegram mobil & iletisim android modlar diger digerleri"}]},{"title":"İletişim & E-posta","links":[{"url":"https://discord.com/","name":"Discord","recommended":false,"description":"Topluluk ve oyun odaklı sohbet platformu.","icon":"icon/discord.svg","alt":"Discord","copyText":"winget install Discord.Discord","tags":["discord"],"folded":"discord discord mobil & iletisim iletisim & e-posta diger digerleri"},{"url":"https://telegram.org/","name":"Telegram","recommended":false,"description":"Güvenli ve hızlı mesajlaşma uygulaması.","icon":"icon/telegram.svg","alt":"Telegram","copyText":"winget install Telegram.TelegramDesktop","tags":["telegram"],"folded":"telegram telegram mobil & iletisim iletisim & e-posta diger digerleri"},{"url":"https://www.whatsapp.com/","name":"WhatsApp","recommended":false,"description":"Popüler, uçtan uca şifreli mesajlaşma ve arama uygulaması.","icon":"icon/whatsapp.svg","alt":"WhatsApp","copyText":"winget install 9NKSQGP7F2NH","tags":["whatsapp"],"folded":"whatsapp whatsapp mobil & iletisim iletisim & e-posta diger digerleri"}]},{"title":"E-posta & Hesap Yönetim","links":[{"url":"https://outlook.live.com/","name":"Outlook","recommended":false,"description":"Microsoft Outlook ile e-posta servisi.","icon":"icon/outlook.svg","alt":"Outlook","tags":["outlook","e-posta","live"],"copyText":"winget install 9NRX63209R7B","folded":"outlook outlook e-posta live mobil & iletisim e-posta & hesap yonetim diger digerleri"},{"url":"https://mail.yahoo.com/","name":"Yahoo Mail","recommended":false,"description":"İle e-posta servisi ve oturum açma.","icon":"icon/yahoo.svg","alt":"Yahoo Mail","tags":["yahoo","mail","e-posta"],"folded":"yahoo mail yahoo mail e-posta mobil & iletisim e-posta & hesap yonetim diger digerleri"},{"url":"https://mail.google.com/","name":"Gmail","recommended":false,"description":"Google Gmail ile e-posta servisi.","icon":"icon/gmail.svg","alt":"Gmail","tags":["gmail","e-posta","mail","google"],"folded":"gmail gmail e-posta mail google mobil & iletisim e-posta & hesap yonetim diger digerleri"},{"url":"https://www.thunderbird.net/tr/","name":"Thunderbird","recommended":false,"description":"Açık kaynaklı, güçlü ve güvenli e-posta istemcisi.","icon":"icon/thunderbird.svg","alt":"Thunderbird","tags":["thunderbird","e-posta"],"copyText":"winget install Mozilla.Thunderbird.tr","folded":"thunderbird thunderbird e-posta mobil & iletisim e-posta & hesap yonetim diger digerleri"}]},{"title":"Spor & Canlı Skor Platformlar","links":[{"url":"https://www.365scores.com/tr","name":"365Scores","recommended":false,"description":"Canlı skorlar, maç sonuçları ve spor haberleri.","icon":"icon/365scores.svg","alt":"365Scores","tags":["365scores"],"folded":"365scores 365scores mobil & iletisim spor & canli skor platformlar diger digerleri"},{"url":"https://www.sofascore.com/tr/","name":"SofaScore","recommended":false,"description":"Canlı skorlar, istatistikler ve spor analizleri.","icon":"icon/sofascore.svg","alt":"SofaScore","tags":["sofascore"],"folded":"sofascore sofascore mobil & iletisim spor & canli skor platformlar diger digerleri"},{"url":"https://www.fotmob.com/tr","name":"FotMob","recommended":false,"description":"Futbol odaklı canlı skor ve haber platformu.","icon":"icon/fotmob.svg","alt":"FotMob","tags":["fotmob"],"folded":"fotmob fotmob mobil & iletisim spor & canli skor platformlar diger digerleri"}]}]}